{"winner":{"border":767.7444547633629,"number":32,"corner":299.1579884784595,"freedom":660.1917635293213,"uuid":"9166aa44-8a2a-4433-bb84-b245ca46dcc1","table":644.9955561957433},"botsInfos":{"Bot10":"1806b7c2-6738-479e-a0ec-681718eb0769","Bot32":"9166aa44-8a2a-4433-bb84-b245ca46dcc1","Bot11":"fde0eaa1-95a6-4e1a-ac08-7e690d48a8c0","Bot33":"f4713a55-da08-40ba-9411-cf3824ae48f3","Bot30":"ef48339d-7724-47ec-ad47-e211e74c10ec","Bot31":"1b5c467b-ed9e-42ae-a5ce-3b16c81e598c","Bot18":"c0d79555-9a08-4a52-8f7a-603d01fc5d21","Bot19":"04e5fb7c-2084-4de1-9164-58f32ef3957a","Bot16":"6f00b3ac-819d-4d89-83a8-1b28fb5b8d78","Bot38":"e2565e1a-b4a4-45e5-afa8-929e8a9a9093","Bot17":"e0cd671a-3fdb-4aff-9783-9d0fd3398f03","Bot39":"042c727b-9275-4f65-84b9-7376b7220aec","Bot14":"f8cb9828-c090-4011-8b6c-715032becc49","Bot36":"10290b1f-2bf6-449e-8b77-f908c31fa2b3","Bot15":"af91b3e5-93cf-4ad4-ab96-8a9f18962d83","Bot37":"a10115ad-3487-404c-928b-365ed9af201c","Bot34":"6468e1ca-7d35-4b9b-8fcf-bb1a8343efde","Bot13":"3e524ace-e78d-43a2-8fac-bc5dc386ca3e","Bot35":"bf258a20-e430-4a0d-ae73-8ae7d8b9aa9b","Bot9":"54c44fc2-1d95-4636-acdd-6530144834aa","Bot7":"8ec52122-ca88-4e58-bc2d-1d3a82457257","Bot21":"0e810f73-1a89-4c93-be14-c594ed182371","Bot43":"b11b9e77-e01a-46b1-81aa-afa714e8d680","Bot6":"655e6b6b-be39-45a1-b713-c065263c5866","Bot22":"0952c8dc-7102-4ac3-aff4-abb77322d905","Bot44":"50fc4478-b4aa-4e5e-9319-c979d7d3e34c","Bot5":"933aea7e-e6c9-40c6-a3af-54fb0ac3ae17","Bot41":"4b8c1ca3-b8c0-48fd-8ab3-b336b757ac97","Bot4":"1278bd6f-612d-4bb9-a372-d97f24b3a895","Bot20":"c046a362-accf-41d8-b2cc-cd1aecbcee3e","Bot3":"b27a8e90-bc24-4a96-9026-2c6d9f4d011b","Bot42":"0004087f-4c25-4492-985c-da9e1e448089","Bot40":"339207ba-f949-41fd-bba2-eb3a4e99a7cf","Bot1":"54c2ef60-2441-41bf-abfa-a440556e12aa","Bot0":"13c53ef7-2fe3-441d-802b-9c24ff5d2ec8","Bot29":"9a4d500d-3806-4389-bf8a-b3588233bcc1","Bot27":"9a09627c-0093-497d-8b30-27677e416a82","Bot49":"2b45c638-cab2-4d31-b1c5-dad13ec6b221","Bot28":"5f6c8217-3d3d-4986-87fd-b9a91e92bc11","Bot25":"4e63e910-b1d3-452a-afc8-1c9c7b2ca188","Bot47":"a3ddb1e7-53a2-409a-9eac-20171280e877","Bot26":"043bbdff-9b2d-4e36-bbe1-301267dfddde","Bot48":"6cf42ef9-2d02-42fb-b8b2-13efa9b1c2e0","Bot23":"5c06f927-b230-47c8-9004-5237e404b593","Bot45":"a02db44f-1aed-4b0d-8683-2bcf82e689ec","Bot24":"6b4c20c6-b5e0-48e2-94d3-07b07f90ce11","Bot46":"e00d9475-11d4-4e27-8b0d-c6f714ab358d"},"finalResults":{"1 | Bot41 - Bot30":0.5,"6 | Bot16 - Bot41":1.0,"8 | Bot38 - Bot16":1.0,"9 | Bot9 - Bot3":1.0,"8 | Bot38 - Bot15":0.5,"1 | Bot41 - Bot32":0.5,"7 | Bot47 - Bot32":1.0,"1 | Bot41 - Bot38":0.5,"2 | Bot32 - Bot16":1.0,"2 | Bot32 - Bot15":1.0,"9 | Bot9 - Bot24":1.0,"5 | Bot15 - Bot47":1.0,"0 | Bot30 - Bot24":1.0,"3 | Bot3 - Bot47":1.0,"7 | Bot47 - Bot38":1.0,"5 | Bot15 - Bot41":1.0,"7 | Bot47 - Bot30":1.0,"3 | Bot3 - Bot41":1.0,"6 | Bot16 - Bot47":1.0,"2 | Bot32 - Bot41":1.0,"0 | Bot30 - Bot38":1.0,"7 | Bot47 - Bot9":1.0,"0 | Bot30 - Bot32":1.0,"4 | Bot24 - Bot16":1.0,"3 | Bot3 - Bot32":1.0,"7 | Bot47 - Bot3":0.5,"9 | Bot9 - Bot16":1.0,"5 | Bot15 - Bot16":1.0,"9 | Bot9 - Bot15":0.5,"1 | Bot41 - Bot47":1.0,"8 | Bot38 - Bot47":1.0,"6 | Bot16 - Bot3":0.5,"4 | Bot24 - Bot15":1.0,"8 | Bot38 - Bot41":1.0,"2 | Bot32 - Bot47":1.0,"6 | Bot16 - Bot9":1.0,"3 | Bot3 - Bot38":1.0,"7 | Bot47 - Bot41":-1.0,"3 | Bot3 - Bot30":1.0,"6 | Bot16 - Bot15":1.0,"2 | Bot32 - Bot30":1.0,"4 | Bot24 - Bot9":-1.0,"1 | Bot41 - Bot16":1.0,"0 | Bot30 - Bot41":1.0,"3 | Bot3 - Bot24":1.0,"4 | Bot24 - Bot47":1.0,"2 | Bot32 - Bot38":1.0,"1 | Bot41 - Bot15":1.0,"9 | Bot9 - Bot47":1.0,"8 | Bot38 - Bot30":1.0,"0 | Bot30 - Bot47":0.5,"5 | Bot15 - Bot24":1.0,"7 | Bot47 - Bot15":1.0,"0 | Bot30 - Bot3":1.0,"8 | Bot38 - Bot32":1.0,"7 | Bot47 - Bot16":1.0,"4 | Bot24 - Bot3":1.0,"4 | Bot24 - Bot41":1.0,"9 | Bot9 - Bot41":1.0,"3 | Bot3 - Bot9":1.0,"0 | Bot30 - Bot9":1.0,"6 | Bot16 - Bot24":1.0,"8 | Bot38 - Bot9":1.0,"6 | Bot16 - Bot30":1.0,"0 | Bot30 - Bot16":1.0,"0 | Bot30 - Bot15":1.0,"1 | Bot41 - Bot24":1.0,"8 | Bot38 - Bot3":1.0,"4 | Bot24 - Bot38":1.0,"9 | Bot9 - Bot38":1.0,"5 | Bot15 - Bot38":1.0,"7 | Bot47 - Bot24":1.0,"8 | Bot38 - Bot24":1.0,"2 | Bot32 - Bot3":1.0,"3 | Bot3 - Bot15":1.0,"1 | Bot41 - Bot9":1.0,"2 | Bot32 - Bot24":1.0,"9 | Bot9 - Bot32":1.0,"3 | Bot3 - Bot16":1.0,"4 | Bot24 - Bot30":0.5,"5 | Bot15 - Bot32":1.0,"9 | Bot9 - Bot30":1.0,"5 | Bot15 - Bot30":1.0,"5 | Bot15 - Bot3":-1.0,"1 | Bot41 - Bot3":1.0,"4 | Bot24 - Bot32":1.0,"2 | Bot32 - Bot9":1.0,"6 | Bot16 - Bot38":1.0,"5 | Bot15 - Bot9":1.0,"6 | Bot16 - Bot32":1.0},"finalScores":{"Bot16 - Reference":0.0,"Bot30 - Reference":0.0,"Bot38 - Reference":0.0,"Bot9 - Reference":0.0,"Bot41 - Reference":0.0,"final":"[19.5, 18.5, 29.5, 21.0, 17.5, 19.0, 18.5, 13.0, 19.0, 19.5]","Bot24 - Reference":0.0,"Bot15 - Reference":0.0,"Bot32 - Reference":2.0,"Bot3 - Reference":0.0,"Bot47 - Reference":-0.5},"groupStageResults":{"group8":{"Bot18 - Bot38":0.5,"Bot9 - Bot48":1.0,"Bot48 - Bot9":1.0,"Bot9 - Bot28":0.5,"Bot48 - Bot38":1.0,"Bot9 - Reference":0.0,"Bot48 - Bot18":1.0,"Bot28 - Bot9":1.0,"Bot28 - Bot48":1.0,"Bot38 - Bot9":1.0,"Bot18 - Reference":-0.5,"Bot28 - Reference":-2.0,"Bot48 - Reference":0.0,"Bot38 - Reference":0.0,"Bot18 - Bot9":1.0,"Bot38 - Bot18":1.0,"Bot9 - Bot38":1.0,"Bot18 - Bot48":1.0,"Bot9 - Bot18":1.0,"Bot48 - Bot28":1.0,"Bot28 - Bot18":1.0,"Bot28 - Bot38":1.0,"Bot18 - Bot28":1.0,"Bot38 - Bot48":1.0,"Bot38 - Bot28":1.0},"group7":{"Bot47 - Bot7":1.0,"Bot17 - Bot37":1.0,"Bot7 - Bot47":-1.0,"Bot7 - Bot27":1.0,"Bot27 - Bot47":1.0,"Bot37 - Bot7":1.0,"Bot37 - Reference":0.0,"Bot7 - Reference":0.0,"Bot47 - Reference":1.5,"Bot17 - Reference":0.0,"Bot37 - Bot17":1.0,"Bot27 - Reference":0.0,"Bot27 - Bot7":1.0,"Bot17 - Bot7":1.0,"Bot47 - Bot27":1.0,"Bot17 - Bot47":1.0,"Bot17 - Bot27":0.5,"Bot7 - Bot37":1.0,"Bot7 - Bot17":1.0,"Bot27 - Bot17":1.0,"Bot27 - Bot37":1.0,"Bot37 - Bot27":1.0,"Bot37 - Bot47":1.0,"Bot47 - Bot17":1.0,"Bot47 - Bot37":0.5},"group9":{"Bot49 - Bot39":1.0,"Bot9 - Bot49":1.0,"Bot49 - Bot9":1.0,"Bot19 - Bot39":1.0,"Bot9 - Bot29":1.0,"Bot29 - Bot9":1.0,"Bot9 - Reference":0.0,"Bot39 - Bot9":1.0,"Bot49 - Bot19":1.0,"Bot39 - Reference":0.0,"Bot29 - Bot49":1.0,"Bot39 - Bot19":1.0,"Bot49 - Reference":0.0,"Bot19 - Bot9":1.0,"Bot19 - Reference":0.0,"Bot29 - Reference":0.0,"Bot19 - Bot29":1.0,"Bot49 - Bot29":1.0,"Bot19 - Bot49":1.0,"Bot9 - Bot39":1.0,"Bot9 - Bot19":1.0,"Bot39 - Bot29":1.0,"Bot29 - Bot19":1.0,"Bot39 - Bot49":1.0,"Bot29 - Bot39":1.0},"group4":{"Bot24 - Bot44":1.0,"Bot34 - Reference":0.0,"Bot34 - Bot4":1.0,"Bot14 - Reference":-2.0,"Bot24 - Reference":0.0,"Bot14 - Bot34":1.0,"Bot44 - Bot4":1.0,"Bot44 - Bot34":1.0,"Bot44 - Bot14":1.0,"Bot4 - Bot34":1.0,"Bot14 - Bot4":1.0,"Bot14 - Bot24":1.0,"Bot4 - Bot14":1.0,"Bot34 - Bot24":1.0,"Bot34 - Bot44":1.0,"Bot24 - Bot4":1.0,"Bot24 - Bot14":1.0,"Bot24 - Bot34":1.0,"Bot14 - Bot44":1.0,"Bot44 - Bot24":0.5,"Bot4 - Bot24":1.0,"Bot4 - Bot44":1.0,"Bot34 - Bot14":1.0,"Bot4 - Reference":-2.0,"Bot44 - Reference":0.0},"group3":{"Bot23 - Bot43":1.0,"Bot23 - Reference":-2.0,"Bot13 - Reference":0.0,"Bot43 - Bot3":1.0,"Bot3 - Bot13":1.0,"Bot3 - Bot33":1.0,"Bot13 - Bot3":1.0,"Bot3 - Bot43":1.0,"Bot43 - Bot33":1.0,"Bot13 - Bot33":1.0,"Bot33 - Bot3":1.0,"Bot43 - Bot13":1.0,"Bot33 - Bot43":1.0,"Bot23 - Bot3":1.0,"Bot33 - Bot23":1.0,"Bot23 - Bot33":1.0,"Bot23 - Bot13":1.0,"Bot3 - Bot23":1.0,"Bot43 - Bot23":1.0,"Bot13 - Bot23":1.0,"Bot13 - Bot43":1.0,"Bot33 - Reference":0.0,"Bot3 - Reference":0.0,"Bot33 - Bot13":1.0,"Bot43 - Reference":-2.0},"group6":{"Bot6 - Reference":0.0,"Bot26 - Bot46":1.0,"Bot36 - Bot6":1.0,"Bot46 - Reference":0.0,"Bot36 - Bot16":1.0,"Bot26 - Reference":-2.0,"Bot36 - Reference":-0.5,"Bot46 - Bot6":0.5,"Bot6 - Bot16":1.0,"Bot16 - Reference":0.0,"Bot16 - Bot26":1.0,"Bot46 - Bot26":1.0,"Bot26 - Bot6":1.0,"Bot6 - Bot36":1.0,"Bot16 - Bot6":1.0,"Bot16 - Bot46":1.0,"Bot26 - Bot16":1.0,"Bot26 - Bot36":1.0,"Bot36 - Bot26":1.0,"Bot36 - Bot46":1.0,"Bot6 - Bot46":1.0,"Bot46 - Bot36":1.0,"Bot6 - Bot26":-1.0,"Bot46 - Bot16":1.0,"Bot16 - Bot36":1.0},"group5":{"Bot5 - Reference":0.0,"Bot45 - Reference":-0.5,"Bot35 - Reference":0.0,"Bot25 - Reference":0.0,"Bot35 - Bot5":1.0,"Bot35 - Bot15":1.0,"Bot45 - Bot35":1.0,"Bot15 - Reference":1.5,"Bot45 - Bot5":0.5,"Bot5 - Bot15":1.0,"Bot5 - Bot35":1.0,"Bot35 - Bot45":-1.0,"Bot15 - Bot45":-1.0,"Bot15 - Bot25":1.0,"Bot25 - Bot5":1.0,"Bot15 - Bot5":1.0,"Bot25 - Bot35":1.0,"Bot25 - Bot15":1.0,"Bot35 - Bot25":1.0,"Bot45 - Bot25":1.0,"Bot5 - Bot25":0.5,"Bot5 - Bot45":1.0,"Bot45 - Bot15":1.0,"Bot15 - Bot35":1.0,"Bot25 - Bot45":1.0},"group0":{"Bot10 - Reference":0.0,"Bot20 - Reference":0.0,"Bot30 - Bot10":1.0,"Bot40 - Reference":0.0,"Bot30 - Reference":1.5,"Bot40 - Bot0":1.0,"Bot40 - Bot20":1.0,"Bot20 - Bot0":1.0,"Bot30 - Bot0":1.0,"Bot10 - Bot0":1.0,"Bot10 - Bot30":1.0,"Bot0 - Bot40":1.0,"Bot0 - Bot20":1.0,"Bot20 - Bot40":1.0,"Bot30 - Bot40":0.5,"Bot30 - Bot20":1.0,"Bot40 - Bot10":1.0,"Bot40 - Bot30":1.0,"Bot0 - Reference":-0.5,"Bot20 - Bot10":1.0,"Bot10 - Bot40":1.0,"Bot10 - Bot20":1.0,"Bot0 - Bot30":1.0,"Bot0 - Bot10":1.0,"Bot20 - Bot30":1.0},"group2":{"Bot32 - Bot13":1.0,"Bot42 - Reference":0.0,"Bot42 - Bot3":1.0,"Bot13 - Reference":-2.0,"Bot3 - Bot13":1.0,"Bot22 - Bot42":1.0,"Bot3 - Bot42":1.0,"Bot13 - Bot3":1.0,"Bot22 - Bot3":1.0,"Bot13 - Bot32":1.0,"Bot32 - Bot3":1.0,"Bot42 - Bot13":1.0,"Bot42 - Bot32":1.0,"Bot32 - Bot42":1.0,"Bot32 - Bot22":1.0,"Bot22 - Bot13":1.0,"Bot3 - Bot22":1.0,"Bot22 - Bot32":1.0,"Bot3 - Bot32":1.0,"Bot13 - Bot22":1.0,"Bot13 - Bot42":1.0,"Bot22 - Reference":-2.0,"Bot32 - Reference":0.0,"Bot42 - Bot22":1.0,"Bot3 - Reference":-2.0},"group1":{"Bot31 - Bot11":1.0,"Bot31 - Reference":-0.5,"Bot21 - Reference":0.0,"Bot21 - Bot41":1.0,"Bot41 - Reference":0.0,"Bot41 - Bot1":1.0,"Bot11 - Bot1":1.0,"Bot41 - Bot31":1.0,"Bot31 - Bot1":1.0,"Bot1 - Bot21":1.0,"Bot41 - Bot11":1.0,"Bot1 - Bot41":1.0,"Bot11 - Bot31":1.0,"Bot21 - Bot1":1.0,"Bot31 - Bot21":1.0,"Bot21 - Bot31":1.0,"Bot21 - Bot11":1.0,"Bot31 - Bot41":0.5,"Bot41 - Bot21":1.0,"Bot1 - Reference":-0.5,"Bot1 - Bot31":1.0,"Bot1 - Bot11":1.0,"Bot11 - Bot21":1.0,"Bot11 - Reference":0.0,"Bot11 - Bot41":1.0}},"groupsInfos":{"group8":["Bot9","Bot18","Bot28","Bot38","Bot48"],"group7":["Bot7","Bot17","Bot27","Bot37","Bot47"],"group9":["Bot9","Bot19","Bot29","Bot39","Bot49"],"group4":["Bot4","Bot14","Bot24","Bot34","Bot44"],"group3":["Bot3","Bot13","Bot23","Bot33","Bot43"],"group6":["Bot6","Bot16","Bot26","Bot36","Bot46"],"group5":["Bot5","Bot15","Bot25","Bot35","Bot45"],"group0":["Bot0","Bot10","Bot20","Bot30","Bot40"],"group2":["Bot3","Bot13","Bot22","Bot32","Bot42"],"group1":["Bot1","Bot11","Bot21","Bot31","Bot41"]},"groupStageScores":{"group8":"[13.5, 8.5, 4.5, 14.5, 14.0]","group7":"[13.0, 13.5, 14.5, 14.5, 19.5]","group9":"[14.0, 14.0, 14.0, 14.0, 14.0]","group4":"[4.0, 4.0, 14.5, 14.0, 13.5]","group3":"[14.0, 14.0, 4.0, 14.0, 4.0]","group6":"[13.5, 14.0, 5.0, 9.0, 13.5]","group5":"[14.0, 18.0, 14.5, 13.0, 10.5]","group0":"[9.0, 14.0, 14.0, 18.5, 14.5]","group2":"[4.0, 4.0, 4.0, 14.0, 14.0]","group1":"[9.0, 14.0, 14.0, 8.5, 14.5]"}}